gaussian_proc/__init__.py
gaussian_proc/__version__.py
gaussian_proc/kernels/linear.pxd
gaussian_proc/kernels/square_exponential.pxd
gaussian_proc/kernels/linear.cpython-36m-darwin.so
gaussian_proc/kernels/exponential.cpython-36m-darwin.so
gaussian_proc/kernels/rational_quadratic.pxd
gaussian_proc/kernels/rational_quadratic.cpython-36m-darwin.so
gaussian_proc/kernels/kernel.pxd
gaussian_proc/kernels/exponential.pyx
gaussian_proc/kernels/__init__.pxd
gaussian_proc/kernels/kernel.cpython-36m-darwin.so
gaussian_proc/kernels/__init__.py
gaussian_proc/kernels/square_exponential.cpython-36m-darwin.so
gaussian_proc/kernels/matern.pyx
gaussian_proc/kernels/matern.pxd
gaussian_proc/kernels/exponential.pxd
gaussian_proc/kernels/kernel.pyx
gaussian_proc/kernels/matern.cpython-36m-darwin.so
gaussian_proc/kernels/rational_quadratic.pyx
gaussian_proc/kernels/linear.pyx
gaussian_proc/kernels/square_exponential.pyx
gaussian_proc/mean/__init__.py
gaussian_proc/mean/linear_model.py
gaussian_proc/priors/inverse_gamma.py
gaussian_proc/priors/erlang.py
gaussian_proc/priors/student_t.py
gaussian_proc/priors/normal.py
gaussian_proc/priors/__init__.py
gaussian_proc/priors/prior.py
gaussian_proc/priors/cauchy.py
gaussian_proc/priors/uniform.py
gaussian_proc/priors/beta_prime.py
gaussian_proc/priors/gamma.py
gaussian_proc/correlation/_sparse_matrix_utilities.pyx
gaussian_proc/correlation/_sparse_auto_correlation.pyx
gaussian_proc/correlation/_dense_cross_correlation.cpython-36m-darwin.so
gaussian_proc/correlation/_compute_sparse_correlation.cpython-36m-darwin.so
gaussian_proc/correlation/_sparse_matrix_utilities.cpython-36m-darwin.so
gaussian_proc/correlation/_sparse_array_utilities.pyx
gaussian_proc/correlation/_compute_dense_correlation.pxd
gaussian_proc/correlation/_dense_cross_correlation.pyx
gaussian_proc/correlation/_compute_dense_correlation.cpython-36m-darwin.so
gaussian_proc/correlation/_compute_sparse_correlation.pyx
gaussian_proc-0.12.6.dist-info/RECORD
gaussian_proc-0.12.6.dist-info/WHEEL
gaussian_proc-0.12.6.dist-info/top_level.txt
gaussian_proc-0.12.6.dist-info/LICENSE.txt
gaussian_proc-0.12.6.dist-info/AUTHORS.txt
gaussian_proc-0.12.6.dist-info/METADATA
