Metadata-Version: 2.1
Name: gaussian_proc
Version: 0.12.6
Summary: Gaussian process regression
Home-page: https://github.com/ameli/gaussian_proc
Author: Siavash Ameli
Author-email: sameli@berkeley.edu
License: UNKNOWN
Download-URL: https://github.com/ameli/gaussian_proc/archive/main.zip
Project-URL: Documentation, https://github.com/ameli/gaussian_proc/blob/main/README.rst
Project-URL: Source, https://github.com/ameli/gaussian_proc
Project-URL: Tracker, https://github.com/ameli/gaussian_proc/issues
Keywords: gaussian-process-regression gaussian-process
Platform: Linux
Platform: OSX
Platform: Windows
Classifier: Programming Language :: Cython
Classifier: Programming Language :: Python
Classifier: Programming Language :: Python :: 3.6
Classifier: Programming Language :: Python :: 3.7
Classifier: Programming Language :: Python :: 3.8
Classifier: Programming Language :: Python :: 3.9
Classifier: Programming Language :: Python :: Implementation :: CPython
Classifier: Programming Language :: Python :: Implementation :: PyPy
Classifier: Environment :: GPU :: NVIDIA CUDA
Classifier: License :: OSI Approved :: BSD License
Classifier: Operating System :: POSIX :: Linux
Classifier: Operating System :: Microsoft :: Windows
Classifier: Operating System :: MacOS
Classifier: Natural Language :: English
Classifier: Intended Audience :: Science/Research
Classifier: Intended Audience :: Developers
Classifier: Topic :: Software Development
Classifier: Topic :: Software Development :: Libraries :: Python Modules
Classifier: Topic :: Scientific/Engineering
Classifier: Topic :: Scientific/Engineering :: Mathematics
Classifier: Topic :: Scientific/Engineering :: Artificial Intelligence
Requires-Python: >=3.6
Provides-Extra: test
Provides-Extra: docs
License-File: LICENSE.txt
License-File: AUTHORS.txt
